prolog/__init__.py
prolog/__main__.py
prolog/__version__.py
prolog/config.py
prolog/formatters.py
prolog/handlers.py
prolog-0.3.1.dist-info/DESCRIPTION.rst
prolog-0.3.1.dist-info/METADATA
prolog-0.3.1.dist-info/RECORD
prolog-0.3.1.dist-info/WHEEL
prolog-0.3.1.dist-info/entry_points.txt
prolog-0.3.1.dist-info/metadata.json
prolog-0.3.1.dist-info/top_level.txt
