Metadata-Version: 1.1
Name: prolog
Version: 0.3.1
Summary: Simple, robust features for expediting application logging configuration
Home-page: https://github.com/dakrauth/prolog
Author: David Krauth
Author-email: dakrauth@gmail.com
License: MIT License
Platform: UNKNOWN
Classifier: License :: OSI Approved :: MIT License
Classifier: Programming Language :: Python
Classifier: Programming Language :: Python :: 3.5
Classifier: Programming Language :: Python :: 3.6
Classifier: Development Status :: 3 - Alpha
Classifier: Environment :: Console
Classifier: Topic :: System :: Logging
Classifier: Topic :: Utilities
